based58-0.1.1.dist-info/METADATA
based58-0.1.1.dist-info/WHEEL
based58-0.1.1.dist-info/license_files/LICENSE
based58.libs/libgcc_s-0d63e1c3.so.1
based58/__init__.py
based58/__init__.pyi
based58/py.typed
based58/based58.abi3.so
based58-0.1.1.dist-info/RECORD
