Metadata-Version: 2.1
Name: based58
Version: 0.1.1
Classifier: Programming Language :: Rust
Classifier: Programming Language :: Python :: Implementation :: CPython
License-File: LICENSE
Summary: A fast Python library for Base58 and Base58Check
Author-email: kevinheavey <kevinheavey123@gmail.com>
Requires-Python: >=3.7
Project-URL: documentation, https://kevinheavey.github.io/based58/
Project-URL: homepage, https://github.com/kevinheavey/based58
Project-URL: repository, https://github.com/kevinheavey/based58
Project-URL: changelog, https://github.com/kevinheavey/based58/blob/main/CHANGELOG.md
